{
  "@defines": {
    "--primary": "rgba(243,139,168,1)",
    "--primary-variant": "rgba(235,160,172,1)",
    "--secondary": "rgba(245,224,220,1)",
    "--secondary-variant": "rgba(128,76,0,1)",
    "--background": "rgba(17,17,27,1)",
    "--surface": "rgba(30,30,46,1)",
    "--surface-variant": "rgba(49,50,68,0.8862745)",
    "--on-background": "rgba(186,194,222,1)",
    "--on-surface": "rgba(205,214,244,1)",
    "--on-surface-variant": "rgba(166,173,200,1)",
    "--shape": "rounded-corner(8dp,8dp,8dp,8dp)",
    "--shape-variant": "rounded-corner(12dp,12dp,12dp,12dp)"
  },
  "keyboard": {
    "background": "var(--background)"
  },
  "key": {
    "background": "var(--surface)",
    "foreground": "var(--on-surface)",
    "font-size": "22sp",
    "shape": "var(--shape)",
    "shadow-elevation": "2dp"
  },
  "key[code=10]": {
    "background": "var(--primary)",
    "foreground": "var(--background)"
  },
  "key[code=32]": {
    "background": "var(--surface)",
    "foreground": "var(--on-surface-variant)",
    "font-size": "12sp"
  },
  "key[code=-11][shiftstate=3]": {
    "foreground": "var(--secondary)"
  },
  "key:pressed": {
    "background": "var(--surface-variant)",
    "foreground": "var(--on-surface)"
  },
  "key[code=10]:pressed": {
    "background": "var(--primary-variant)",
    "foreground": "var(--on-surface)"
  },
  "key-hint": {
    "background": "rgba(0,0,0,0)",
    "foreground": "var(--on-surface-variant)",
    "font-size": "12sp"
  },
  "key-popup": {
    "background": "rgba(49,50,68,1)",
    "foreground": "var(--on-surface)",
    "font-size": "22sp",
    "shape": "var(--shape)",
    "shadow-elevation": "2dp"
  },
  "key-popup:focus": {
    "background": "rgba(69,71,90,1)",
    "foreground": "var(--on-surface)"
  },
  "smartbar-primary-actions-toggle": {
    "background": "var(--surface)",
    "foreground": "var(--on-surface)",
    "shape": "circle()",
    "shadow-elevation": "2dp"
  },
  "smartbar-secondary-actions-toggle": {
    "background": "rgba(0,0,0,0)",
    "foreground": "var(--on-surface-variant)",
    "shape": "circle()"
  },
  "smartbar-quick-action": {
    "background": "rgba(0,0,0,0)",
    "foreground": "var(--on-background)",
    "shape": "circle()"
  },
  "smartbar-key": {
    "background": "rgba(0,0,0,0)",
    "foreground": "var(--on-background)",
    "font-size": "18sp",
    "shape": "var(--shape)"
  },
  "smartbar-key:pressed": {
    "background": "var(--surface)",
    "foreground": "var(--on-surface)"
  },
  "smartbar-key:disabled": {
    "background": "rgba(0,0,0,0)",
    "foreground": "rgba(220,220,220,0.28235295)"
  },
  "smartbar-candidate-word": {
    "background": "rgba(0,0,0,0)",
    "foreground": "var(--on-background)",
    "font-size": "14sp",
    "shape": "rectangle()"
  },
  "smartbar-candidate-word:pressed": {
    "background": "var(--surface)",
    "foreground": "var(--on-background)"
  },
  "smartbar-candidate-clip": {
    "background": "rgba(0,0,0,0)",
    "foreground": "var(--on-background)",
    "font-size": "14sp",
    "shape": "rounded-corner(8%,8%,8%,8%)"
  },
  "smartbar-candidate-clip:pressed": {
    "background": "var(--surface)",
    "foreground": "var(--on-background)"
  },
  "smartbar-candidate-spacer": {
    "foreground": "var(--surface)"
  },
  "clipboard-header": {
    "background": "rgba(0,0,0,0)",
    "foreground": "var(--on-surface)",
    "font-size": "16sp"
  },
  "clipboard-item": {
    "background": "var(--surface)",
    "foreground": "var(--on-surface)",
    "font-size": "14sp",
    "shape": "var(--shape-variant)",
    "shadow-elevation": "2dp"
  },
  "clipboard-item-popup": {
    "background": "var(--surface-variant)",
    "foreground": "var(--on-surface)",
    "font-size": "14sp",
    "shape": "var(--shape-variant)",
    "shadow-elevation": "2dp"
  },
  "emoji-key": {
    "background": "rgba(0,0,0,0)",
    "foreground": "var(--on-background)",
    "font-size": "22sp",
    "shape": "var(--shape)"
  },
  "emoji-key:pressed": {
    "background": "var(--surface)",
    "foreground": "var(--on-surface)"
  },
  "emoji-key-popup": {
    "background": "rgba(117,117,117,1)",
    "foreground": "var(--on-surface)",
    "font-size": "22sp",
    "shape": "var(--shape)",
    "shadow-elevation": "2dp"
  },
  "emoji-tab": {
    "foreground": "var(--on-background)"
  },
  "emoji-tab:focus": {
    "foreground": "var(--primary)"
  },
  "extracted-landscape-input-action": {
    "background": "var(--surface)",
    "foreground": "var(--on-surface)",
    "shape": "rounded-corner(4dp,4dp,4dp,4dp)"
  },
  "extracted-landscape-input-field": {
    "background": "rgba(0,0,0,0)",
    "foreground": "var(--on-background)",
    "font-size": "16sp",
    "shape": "rounded-corner(12dp,12dp,12dp,12dp)",
    "border-color": "var(--secondary-variant)",
    "border-width": "1dp"
  },
  "extracted-landscape-input-layout": {
    "background": "var(--background)"
  },
  "glide-trail": {
    "foreground": "var(--primary-variant)"
  },
  "one-handed-panel": {
    "background": "var(--background)",
    "foreground": "var(--on-surface)"
  },
  "system-nav-bar": {
    "background": "var(--background)"
  }
}
